MANIFEST.in
README.rst
setup.cfg
setup.py
bnrml_usaddress/__init__.py
bnrml_usaddress/cli.py
bnrml_usaddress/errors.py
bnrml_usaddress/parsing.py
bnrml_usaddress/strutils.py
bnrml_usaddress/version.py
bnrml_usaddress.egg-info/PKG-INFO
bnrml_usaddress.egg-info/SOURCES.txt
bnrml_usaddress.egg-info/dependency_links.txt
bnrml_usaddress.egg-info/entry_points.txt
bnrml_usaddress.egg-info/requires.txt
bnrml_usaddress.egg-info/top_level.txt
bnrml_usaddress/normalizers/__init__.py
bnrml_usaddress/normalizers/addrnums.py
bnrml_usaddress/normalizers/config.py
bnrml_usaddress/normalizers/numbers.py
bnrml_usaddress/normalizers/streetnames.py
bnrml_usaddress/normalizers/normals/addressnumber.toml
bnrml_usaddress/normalizers/normals/placename.toml
bnrml_usaddress/normalizers/normals/statename.toml
bnrml_usaddress/normalizers/normals/streetname.toml
bnrml_usaddress/normalizers/normals/streetnamepostdirectional.toml
bnrml_usaddress/normalizers/normals/streetnameposttype.toml
bnrml_usaddress/normalizers/normals/streetnamepredirectional.toml