Metadata-Version: 1.2
Name: bnrml-usaddress
Version: 0.0.8
Summary: Parse and normalize unstructured US address strings!
Home-page: https://github.com/patdaburu/bnrml_usaddress
Author: Pat Daburu
Author-email: pat@daburu.net
License: MIT
Download-URL: https://github.com/patdaburu/bnrml_usaddress/archive/0.0.8.tar.gz
Platform: UNKNOWN
Classifier: Development Status :: 3 - Alpha
Classifier: Intended Audience :: Developers
Classifier: Topic :: Software Development :: Libraries
Classifier: License :: OSI Approved :: MIT License
Classifier: Programming Language :: Python :: 3.6
Requires-Python: >=0.0.1
